Metadata-Version: 1.2
Name: basevar
Version: 0.0.1.3
Summary: BaseVar: A python software for calling variants from ultra low pass WGS data.
Home-page: https://github.com/ShujiaHuang/basevar
Author: Shujia Huang & Siyang Liu
Author-email: huangshujia9@gmail.com
Maintainer: Shujia Huang & Siyang Liu
Maintainer-email: huangshujia9@gmail.com
License: BSD (3-clause)
Download-URL: https://github.com/ShujiaHuang/basevar
Platform: UNKNOWN
Classifier: Intended Audience :: Science/Research
Classifier: Programming Language :: Python :: 2.7
Classifier: Programming Language :: Python :: 3.7
Classifier: License :: OSI Approved :: BSD License
Classifier: Topic :: Scientific/Engineering :: Bio-Informatics
Classifier: Operating System :: POSIX
Classifier: Operating System :: POSIX :: Linux
Classifier: Operating System :: MacOS
